neuronexus/__init__.py
neuronexus/aiohttp_ip_rotator/__init__.py
neuronexus/aiohttp_ip_rotator/rotator.py
NeuroNexus-1.0.1.dist-info/LICENSE
NeuroNexus-1.0.1.dist-info/METADATA
NeuroNexus-1.0.1.dist-info/WHEEL
NeuroNexus-1.0.1.dist-info/top_level.txt
NeuroNexus-1.0.1.dist-info/RECORD
