Metadata-Version: 2.1
Name: NeuroNexus
Version: 1.0.1
Summary: Prive.
Author: NorkzYT
License-File: LICENSE
Requires-Dist: beautifulsoup4
Requires-Dist: requests
